diffcalc/__init__.py
diffcalc/util.py
diffcalc/hkl/__init__.py
diffcalc/hkl/calc.py
diffcalc/hkl/calc_detector.py
diffcalc/hkl/calc_func.py
diffcalc/hkl/calc_reference.py
diffcalc/hkl/calc_sample.py
diffcalc/hkl/constraints.py
diffcalc/hkl/geometry.py
diffcalc/ub/__init__.py
diffcalc/ub/calc.py
diffcalc/ub/crystal.py
diffcalc/ub/fitting.py
diffcalc/ub/reference.py
diffcalc_core-0.4.0.dist-info/LICENSE
diffcalc_core-0.4.0.dist-info/METADATA
diffcalc_core-0.4.0.dist-info/WHEEL
diffcalc_core-0.4.0.dist-info/top_level.txt
diffcalc_core-0.4.0.dist-info/RECORD
