Metadata-Version: 2.1
Name: diffcalc-core
Version: 0.4.0
Summary: Diffraction Condition Calculator
Home-page: UNKNOWN
Author: Diamond Light Source
Author-email: scientificsoftware@diamond.ac.uk
License: Apache License, Version 2.0
Project-URL: Documentation, https://diffcalc-core.readthedocs.io/
Project-URL: GitHub, https://github.com/DiamondLightSource/diffcalc-core
Project-URL: Bug-Tracker, https://github.com/DiamondLightSource/diffcalc-core/issues
Keywords: diffcalc,diffractometer,x-ray,neutron
Platform: UNKNOWN
Classifier: Development Status :: 3 - Alpha
Classifier: Intended Audience :: Developers
Classifier: License :: OSI Approved :: Apache Software License
Classifier: Natural Language :: English
Classifier: Programming Language :: Python :: 3
Classifier: Programming Language :: Python :: 3.7
Classifier: Programming Language :: Python :: 3.8
Classifier: Programming Language :: Python :: 3.9
Classifier: Programming Language :: Python :: 3.10
Requires-Python: >=3.7
Requires-Dist: numpy
Requires-Dist: scipy
Requires-Dist: typing-extensions
